gait/__init__.py
gait/__main__.py
gait/diff.py
gait/errors.py
gait/main.py
gait/system_prompts/default
gait/utils.py
gait-0.1.1.dist-info/LICENSE
gait-0.1.1.dist-info/METADATA
gait-0.1.1.dist-info/WHEEL
gait-0.1.1.dist-info/entry_points.txt
gait-0.1.1.dist-info/RECORD
