Metadata-Version: 2.1
Name: gait
Version: 0.1.1
Summary: Review your code changes in a git repository using an LLM
Home-page: https://github.com/can-taslicukur/gait
License: Apache-2.0
Author: Can Taşlıçukur
Author-email: can.taslicukur@ozu.edu.tr
Requires-Python: >=3.8,<4.0
Classifier: License :: OSI Approved :: Apache Software License
Classifier: Programming Language :: Python :: 3
Classifier: Programming Language :: Python :: 3.8
Classifier: Programming Language :: Python :: 3.9
Classifier: Programming Language :: Python :: 3.10
Classifier: Programming Language :: Python :: 3.11
Classifier: Programming Language :: Python :: 3.12
Requires-Dist: gitpython (>=3.1.42,<4.0.0)
Requires-Dist: openai (>=1.12.0,<2.0.0)
Requires-Dist: typer[all] (>=0.9.0,<0.10.0)
Project-URL: Repository, https://github.com/can-taslicukur/gait
